onnxruntime_macavx-1.12.0.data/purelib/onnxruntime/LICENSE
onnxruntime_macavx-1.12.0.data/purelib/onnxruntime/Privacy.md
onnxruntime_macavx-1.12.0.data/purelib/onnxruntime/ThirdPartyNotices.txt
onnxruntime_macavx-1.12.0.data/purelib/onnxruntime/__init__.py
onnxruntime_macavx-1.12.0.data/purelib/onnxruntime/backend/__init__.py
onnxruntime_macavx-1.12.0.data/purelib/onnxruntime/backend/backend.py
onnxruntime_macavx-1.12.0.data/purelib/onnxruntime/backend/backend_rep.py
onnxruntime_macavx-1.12.0.data/purelib/onnxruntime/capi/__init__.py
onnxruntime_macavx-1.12.0.data/purelib/onnxruntime/capi/_ld_preload.py
onnxruntime_macavx-1.12.0.data/purelib/onnxruntime/capi/_pybind_state.py
onnxruntime_macavx-1.12.0.data/purelib/onnxruntime/capi/libmaca-vx.so
onnxruntime_macavx-1.12.0.data/purelib/onnxruntime/capi/libonnxruntime_providers_shared.so
onnxruntime_macavx-1.12.0.data/purelib/onnxruntime/capi/onnxruntime_collect_build_info.py
onnxruntime_macavx-1.12.0.data/purelib/onnxruntime/capi/onnxruntime_inference_collection.py
onnxruntime_macavx-1.12.0.data/purelib/onnxruntime/capi/onnxruntime_pybind11_state.so
onnxruntime_macavx-1.12.0.data/purelib/onnxruntime/capi/onnxruntime_validation.py
onnxruntime_macavx-1.12.0.data/purelib/onnxruntime/capi/training/__init__.py
onnxruntime_macavx-1.12.0.data/purelib/onnxruntime/datasets/__init__.py
onnxruntime_macavx-1.12.0.data/purelib/onnxruntime/datasets/logreg_iris.onnx
onnxruntime_macavx-1.12.0.data/purelib/onnxruntime/datasets/mul_1.onnx
onnxruntime_macavx-1.12.0.data/purelib/onnxruntime/datasets/sigmoid.onnx
onnxruntime_macavx-1.12.0.data/purelib/onnxruntime/quantization/__init__.py
onnxruntime_macavx-1.12.0.data/purelib/onnxruntime/quantization/calibrate.py
onnxruntime_macavx-1.12.0.data/purelib/onnxruntime/quantization/onnx_model.py
onnxruntime_macavx-1.12.0.data/purelib/onnxruntime/quantization/onnx_quantizer.py
onnxruntime_macavx-1.12.0.data/purelib/onnxruntime/quantization/qdq_quantizer.py
onnxruntime_macavx-1.12.0.dist-info/METADATA
onnxruntime_macavx-1.12.0.dist-info/WHEEL
onnxruntime_macavx-1.12.0.dist-info/entry_points.txt
onnxruntime_macavx-1.12.0.dist-info/top_level.txt
onnxruntime_macavx-1.12.0.dist-info/RECORD
